pyk/__init__.py
pyk/__main__.py
pyk/coverage.py
pyk/dequote.py
pyk/kcovr.py
pyk/py.typed
pyk/utils.py
pyk/cli/args.py
pyk/cli/cli.py
pyk/cli/pyk.py
pyk/cli/utils.py
pyk/cterm/__init__.py
pyk/cterm/cterm.py
pyk/cterm/show.py
pyk/cterm/symbolic.py
pyk/kast/__init__.py
pyk/kast/_ast_to_kast.py
pyk/kast/att.py
pyk/kast/color.py
pyk/kast/formatter.py
pyk/kast/inner.py
pyk/kast/kast.py
pyk/kast/lexer.py
pyk/kast/manip.py
pyk/kast/markdown.py
pyk/kast/outer.py
pyk/kast/outer_lexer.py
pyk/kast/outer_parser.py
pyk/kast/outer_syntax.py
pyk/kast/parser.py
pyk/kast/pretty.py
pyk/kast/rewrite.py
pyk/kast/utils.py
pyk/kast/prelude/__init__.py
pyk/kast/prelude/bytes.py
pyk/kast/prelude/collections.py
pyk/kast/prelude/k.py
pyk/kast/prelude/kbool.py
pyk/kast/prelude/kint.py
pyk/kast/prelude/ml.py
pyk/kast/prelude/string.py
pyk/kast/prelude/utils.py
pyk/kbuild/__init__.py
pyk/kbuild/__main__.py
pyk/kbuild/config.py
pyk/kbuild/kbuild.py
pyk/kbuild/project.py
pyk/kbuild/utils.py
pyk/kcfg/__init__.py
pyk/kcfg/exploration.py
pyk/kcfg/explore.py
pyk/kcfg/kcfg.py
pyk/kcfg/minimize.py
pyk/kcfg/semantics.py
pyk/kcfg/show.py
pyk/kcfg/store.py
pyk/kcfg/style.css
pyk/kcfg/tui.py
pyk/kdist/README.md
pyk/kdist/__init__.py
pyk/kdist/__main__.py
pyk/kdist/_cache.py
pyk/kdist/_kdist.py
pyk/kdist/api.py
pyk/kdist/utils.py
pyk/klean/README.md
pyk/klean/__init__.py
pyk/klean/__main__.py
pyk/klean/generate.py
pyk/klean/k2lean4.py
pyk/klean/model.py
pyk/klean/template/cookiecutter.json
pyk/klean/template/{{ cookiecutter.package_name }}/.gitignore
pyk/klean/template/{{ cookiecutter.package_name }}/lakefile.toml
pyk/klean/template/{{ cookiecutter.package_name }}/lean-toolchain
pyk/klean/template/{{ cookiecutter.package_name }}/{{ cookiecutter.library_name }}.lean
pyk/klean/template/{{ cookiecutter.package_name }}/{{ cookiecutter.library_name }}/Prelude.lean
pyk/kllvm/__init__.py
pyk/kllvm/ast.py
pyk/kllvm/compiler.py
pyk/kllvm/convert.py
pyk/kllvm/importer.py
pyk/kllvm/load.py
pyk/kllvm/load_static.py
kframework-7.1.313.dist-info/METADATA
kframework-7.1.313.dist-info/WHEEL
kframework-7.1.313.dist-info/entry_points.txt
kframework-7.1.313.dist-info/licenses/LICENSE.md
kframework-7.1.313.dist-info/RECORD
